oanda_v20_platform/__init__.py
oanda_v20_platform/main.py
oanda_v20_platform/config/__init__.py
oanda_v20_platform/config/args.py
oanda_v20_platform/config/config.ini
oanda_v20_platform/data/__init__.py
oanda_v20_platform/data/marketdata.py
oanda_v20_platform/indicators/__init__.py
oanda_v20_platform/indicators/indicators.py
oanda_v20_platform/notifier/__init__.py
oanda_v20_platform/notifier/email.py
oanda_v20_platform/notifier/sms.py
oanda_v20_platform/oanda/__init__.py
oanda_v20_platform/oanda/oanda.py
oanda_v20_platform/strategies/__init__.py
oanda_v20_platform/strategies/forex_bots_python/__init__.py
oanda_v20_platform/strategies/forex_bots_python/price_printer.py
oanda_v20_platform/strategies/forex_bots_python/rsi_bot.py
oanda_v20_platform/strategies/forex_bots_python/simple_order_bot.py
oanda_v20_platform/utils/__init__.py
oanda_v20_platform/utils/fileops.py
oanda_v20_platform/utils/hardware_usage.py
oanda_v20_platform/utils/timer.py
oanda_v20_platform_ant358-0.1.1.dist-info/LICENSE
oanda_v20_platform_ant358-0.1.1.dist-info/METADATA
oanda_v20_platform_ant358-0.1.1.dist-info/WHEEL
oanda_v20_platform_ant358-0.1.1.dist-info/top_level.txt
oanda_v20_platform_ant358-0.1.1.dist-info/RECORD
