Metadata-Version: 2.1
Name: oanda-v20-platform-ant358
Version: 0.1.1
Summary: A platform to enable automated trading and market analysis with Python on the Oanda brokerage API
Home-page: https://github.com/ant358/oanda_v20_platform_public
Author: Eric Lingren, Anthony Wynne
Author-email: 12174019+ant358@users.noreply.github.com
License: BSD 4-Clause License
Project-URL: Bug Tracker, https://github.com/ant358/oanda_v20_platform_public/issues
Project-URL: Upstream Remote, https://github.com/Eric-Lingren/oanda_v20_platform_public
Keywords: python,finance,oanda,trading,forex,cfd
Platform: UNKNOWN
Classifier: Development Status :: 3 - Alpha
Classifier: Intended Audience :: Developers
Classifier: Programming Language :: Python :: 3.7
Classifier: License :: OSI Approved :: BSD License
Classifier: Operating System :: OS Independent
Requires-Python: >=3.7
License-File: LICENSE
Requires-Dist: ipykernel (==5.5.3)
Requires-Dist: numpy (==1.20.2)
Requires-Dist: packaging (==20.9)
Requires-Dist: pandas (==1.2.4)
Requires-Dist: psutil (==5.8.0)
Requires-Dist: pytest (==6.2.4)
Requires-Dist: python-decouple (==3.4)
Requires-Dist: requests (==2.25.1)
Requires-Dist: schedule (==1.1.0)
Requires-Dist: SQLAlchemy (==1.4.14)
Requires-Dist: tulipy (==0.4.0)
Requires-Dist: twilio (==6.57.0)
Requires-Dist: urllib3 (==1.26.4)
